[
  {
    "batch_size": 256,
    "dataset": "mnist",
    "device": "mps",
    "epochs": 10,
    "final_train_loss": 0.04030117119880433,
    "latent_dim": 2,
    "learning_rate": 0.001,
    "model_parameters": 469010,
    "sample_count": 10,
    "seed": 42,
    "source": "trained",
    "test_mse": 0.04051805241033435,
    "test_psnr": 13.923514381333948,
    "test_ssim": 0.7146218657493592
  },
  {
    "batch_size": 256,
    "dataset": "mnist",
    "device": "mps",
    "epochs": 10,
    "final_train_loss": 0.020080418258588365,
    "latent_dim": 8,
    "learning_rate": 0.001,
    "model_parameters": 470552,
    "sample_count": 10,
    "seed": 42,
    "source": "trained",
    "test_mse": 0.019824356446042656,
    "test_psnr": 17.028009021929048,
    "test_ssim": 0.8754331544041634
  },
  {
    "batch_size": 256,
    "dataset": "mnist",
    "device": "mps",
    "epochs": 10,
    "final_train_loss": 0.013730045443678156,
    "latent_dim": 16,
    "learning_rate": 0.001,
    "model_parameters": 472608,
    "sample_count": 10,
    "seed": 42,
    "source": "trained",
    "test_mse": 0.013315183320082724,
    "test_psnr": 18.756528499270836,
    "test_ssim": 0.9189563438296318
  },
  {
    "batch_size": 256,
    "dataset": "mnist",
    "device": "mps",
    "epochs": 10,
    "final_train_loss": 0.012000517131007733,
    "latent_dim": 32,
    "learning_rate": 0.001,
    "model_parameters": 476720,
    "sample_count": 10,
    "seed": 42,
    "source": "trained",
    "test_mse": 0.011398359597660602,
    "test_psnr": 19.431576459394634,
    "test_ssim": 0.9321262896060943
  },
  {
    "batch_size": 256,
    "dataset": "mnist",
    "device": "mps",
    "epochs": 10,
    "final_train_loss": 0.01216369472206273,
    "latent_dim": 64,
    "learning_rate": 0.001,
    "model_parameters": 484944,
    "sample_count": 10,
    "seed": 42,
    "source": "trained",
    "test_mse": 0.011496558785438538,
    "test_psnr": 19.39432135658903,
    "test_ssim": 0.931069801747799
  }
]